visiongui/__init__.py
visiongui/app/VisiongraphApp.py
visiongui/app/VisiongraphAppLauncher.py
visiongui/app/__init__.py
visiongui/configuration/ConfigurationDialog.py
visiongui/configuration/InputConfiguration.py
visiongui/configuration/__init__.py
visiongui/ui/BaseUserInterface.py
visiongui/ui/UIContext.py
visiongui/ui/VisiongraphUserInterface.py
visiongui/ui/__init__.py
visiongui/utils/ImageWidgetHelper.py
visiongui/utils/KeyStrokeDetector.py
visiongui/utils/__init__.py
visiongui/widgets/ApplicationMenu.py
visiongui/widgets/__init__.py
visiongraph_ui-0.3.0.dist-info/METADATA
visiongraph_ui-0.3.0.dist-info/WHEEL
visiongraph_ui-0.3.0.dist-info/top_level.txt
visiongraph_ui-0.3.0.dist-info/RECORD
