Metadata-Version: 2.1
Name: visiongraph-ui
Version: 0.3.0
Summary: User interface library for visiongraph projects.
Home-page: https://github.com/cansik/visiongraph-ui
Author: Florian Bruggisser
Author-email: github@broox.ch
License: MIT License
Platform: UNKNOWN
Requires-Dist: visiongraph>=1.0.0b1
Requires-Dist: duit[open3d]>=0.1.7.2
Requires-Dist: ConfigArgParse
Provides-Extra: all
